<?xml version="1.0" encoding="UTF-8" ?>

<node name="/">
  <interface name="org.gnome.Gossip">
    <method name="SetPresence">
      <arg name="state" type="s" direction="in"/>
      <arg name="status" type="s" direction="in"/>
    </method>
    <method name="SetNotAway">
    </method>
    <method name="SetNetworkStatus">
      <arg name="up" type="b" direction="in"/>
    </method>
    <method name="SetRosterVisible">
      <arg name="visible" type="b" direction="in"/>
    </method>
    <method name="GetPresence">
      <arg name="contact" type="s" direction="in"/>
      <arg name="state" type="s" direction="out"/>
      <arg name="status" type="s" direction="out"/>
    </method>
    <method name="GetName">
      <arg name="contact" type="s" direction="in"/>
      <arg name="name" type="s" direction="out"/>
    </method>
    <method name="GetRosterVisible">
      <arg name="visible" type="b" direction="out"/>
    </method>
    <method name="GetOpenChats">
      <arg name="contacts" type="as" direction="out"/>
    </method>
    <method name="SendMessage">
      <arg name="contact" type="s" direction="in"/>
    </method>
    <method name="NewMessage">
    </method>
    <method name="ToggleRoster">
    </method>
  </interface>
</node>

